{
    "constructors": [],
    "externalReferences": [],
    "id": "01p4C0000002iHZQAY",
    "innerClasses": [
        {
            "constructors": [],
            "externalReferences": [],
            "id": null,
            "innerClasses": [],
            "interfaces": [],
            "key": null,
            "methods": [],
            "name": "permsException",
            "namespace": null,
            "parentClass": "Exception",
            "properties": [],
            "tableDeclaration": {
                "annotations": [],
                "location": {
                    "column": 19,
                    "line": 40
                },
                "modifiers": [
                    "private"
                ],
                "name": "permsException",
                "references": [],
                "type": "permsException"
            },
            "variables": []
        },
        {
            "constructors": [
                {
                    "annotations": [],
                    "location": {
                        "column": 16,
                        "line": 682
                    },
                    "modifiers": [
                        "public"
                    ],
                    "name": "SelectOption",
                    "parameters": [
                        {
                            "name": "strLabel",
                            "type": "String"
                        },
                        {
                            "name": "strValue",
                            "type": "String"
                        }
                    ],
                    "references": [],
                    "type": null
                }
            ],
            "externalReferences": [],
            "id": null,
            "innerClasses": [],
            "interfaces": [],
            "key": null,
            "methods": [],
            "name": "SelectOption",
            "namespace": null,
            "parentClass": "",
            "properties": [
                {
                    "annotations": [],
                    "location": {
                        "column": 23,
                        "line": 688
                    },
                    "modifiers": [
                        "public"
                    ],
                    "name": "label",
                    "references": [],
                    "type": "String"
                },
                {
                    "annotations": [],
                    "location": {
                        "column": 23,
                        "line": 691
                    },
                    "modifiers": [
                        "public"
                    ],
                    "name": "value",
                    "references": [],
                    "type": "String"
                }
            ],
            "tableDeclaration": {
                "annotations": [],
                "location": {
                    "column": 18,
                    "line": 680
                },
                "modifiers": [
                    "public"
                ],
                "name": "SelectOption",
                "references": [],
                "type": "SelectOption"
            },
            "variables": [
                {
                    "annotations": [],
                    "location": {
                        "column": 36,
                        "line": 682
                    },
                    "modifiers": [],
                    "name": "strLabel",
                    "references": [],
                    "type": "String"
                },
                {
                    "annotations": [],
                    "location": {
                        "column": 53,
                        "line": 682
                    },
                    "modifiers": [],
                    "name": "strValue",
                    "references": [],
                    "type": "String"
                }
            ]
        }
    ],
    "interfaces": [],
    "key": "01p4C0000002iHZQAY",
    "methods": [
        {
            "annotations": [],
            "location": {
                "column": 24,
                "line": 46
            },
            "modifiers": [
                "static",
                "public"
            ],
            "name": "packageLabels",
            "parameters": [],
            "references": [],
            "returnType": "void",
            "type": null
        },
        {
            "annotations": [],
            "location": {
                "column": 27,
                "line": 83
            },
            "modifiers": [
                "static",
                "public"
            ],
            "name": "getHH",
            "parameters": [
                {
                    "name": "hhId",
                    "type": "Id"
                }
            ],
            "references": [],
            "returnType": "SObject",
            "type": null
        },
        {
            "annotations": [],
            "location": {
                "column": 33,
                "line": 115
            },
            "modifiers": [
                "private",
                "static"
            ],
            "name": "getUpdateableHouseholdFields",
            "parameters": [
                {
                    "name": "isHHAccount",
                    "type": "Boolean"
                }
            ],
            "references": [],
            "returnType": "LIST",
            "type": null
        },
        {
            "annotations": [],
            "location": {
                "column": 33,
                "line": 141
            },
            "modifiers": [
                "static",
                "public"
            ],
            "name": "getContacts",
            "parameters": [
                {
                    "name": "hhId",
                    "type": "Id"
                }
            ],
            "references": [],
            "returnType": "LIST",
            "type": null
        },
        {
            "annotations": [],
            "location": {
                "column": 26,
                "line": 174
            },
            "modifiers": [
                "static",
                "public"
            ],
            "name": "getContactSelectQueryWithFls",
            "parameters": [],
            "references": [],
            "returnType": "String",
            "type": null
        },
        {
            "annotations": [],
            "location": {
                "column": 33,
                "line": 209
            },
            "modifiers": [
                "private",
                "static"
            ],
            "name": "getContactFields",
            "parameters": [],
            "references": [],
            "returnType": "LIST",
            "type": null
        },
        {
            "annotations": [],
            "location": {
                "column": 32,
                "line": 253
            },
            "modifiers": [
                "private",
                "static"
            ],
            "name": "setUpdateableContactFields",
            "parameters": [],
            "references": [],
            "returnType": "Set",
            "type": null
        },
        {
            "annotations": [],
            "location": {
                "column": 27,
                "line": 280
            },
            "modifiers": [
                "static",
                "public"
            ],
            "name": "isDeletable",
            "parameters": [
                {
                    "name": "strSObject",
                    "type": "String"
                }
            ],
            "references": [],
            "returnType": "Boolean",
            "type": null
        },
        {
            "annotations": [],
            "location": {
                "column": 24,
                "line": 296
            },
            "modifiers": [
                "static",
                "public"
            ],
            "name": "upsertContacts",
            "parameters": [
                {
                    "name": "listCon",
                    "type": "LIST"
                }
            ],
            "references": [],
            "returnType": "void",
            "type": null
        },
        {
            "annotations": [],
            "location": {
                "column": 24,
                "line": 371
            },
            "modifiers": [
                "static",
                "public"
            ],
            "name": "updateHousehold",
            "parameters": [
                {
                    "name": "hh",
                    "type": "SObject"
                }
            ],
            "references": [],
            "returnType": "void",
            "type": null
        },
        {
            "annotations": [],
            "location": {
                "column": 24,
                "line": 418
            },
            "modifiers": [
                "static",
                "public"
            ],
            "name": "mergeHouseholds",
            "parameters": [
                {
                    "name": "hhWinner",
                    "type": "Account"
                },
                {
                    "name": "listHHMerge",
                    "type": "LIST"
                }
            ],
            "references": [],
            "returnType": "void",
            "type": null
        },
        {
            "annotations": [],
            "location": {
                "column": 24,
                "line": 442
            },
            "modifiers": [
                "static",
                "public"
            ],
            "name": "saveHouseholdPage",
            "parameters": [
                {
                    "name": "hh",
                    "type": "SObject"
                },
                {
                    "name": "listCon",
                    "type": "LIST"
                },
                {
                    "name": "listConRemove",
                    "type": "LIST"
                },
                {
                    "name": "listHHMerge",
                    "type": "LIST"
                }
            ],
            "references": [],
            "returnType": "void",
            "type": null
        },
        {
            "annotations": [],
            "location": {
                "column": 27,
                "line": 468
            },
            "modifiers": [
                "static",
                "public"
            ],
            "name": "getHHNamesGreetings",
            "parameters": [
                {
                    "name": "hh",
                    "type": "SObject"
                },
                {
                    "name": "listCon",
                    "type": "LIST"
                }
            ],
            "references": [],
            "returnType": "SObject",
            "type": null
        },
        {
            "annotations": [],
            "location": {
                "column": 36,
                "line": 499
            },
            "modifiers": [
                "static",
                "public"
            ],
            "name": "getAddresses",
            "parameters": [
                {
                    "name": "hhId",
                    "type": "Id"
                },
                {
                    "name": "listAddrExisting",
                    "type": "LIST"
                }
            ],
            "references": [],
            "returnType": "LIST",
            "type": null
        },
        {
            "annotations": [],
            "location": {
                "column": 36,
                "line": 616
            },
            "modifiers": [
                "static",
                "public"
            ],
            "name": "addContactAddresses",
            "parameters": [
                {
                    "name": "listCon",
                    "type": "LIST"
                },
                {
                    "name": "listAddrExisting",
                    "type": "LIST"
                }
            ],
            "references": [],
            "returnType": "LIST",
            "type": null
        },
        {
            "annotations": [],
            "location": {
                "column": 38,
                "line": 661
            },
            "modifiers": [
                "static",
                "public"
            ],
            "name": "getSalutations",
            "parameters": [],
            "references": [],
            "returnType": "LIST",
            "type": null
        }
    ],
    "name": "HH_Container_LCTRL",
    "namespace": null,
    "parentClass": "",
    "properties": [],
    "tableDeclaration": {
        "annotations": [],
        "location": {
            "column": 27,
            "line": 37
        },
        "modifiers": [
            "public",
            "with sharing"
        ],
        "name": "HH_Container_LCTRL",
        "references": [],
        "type": "HH_Container_LCTRL"
    },
    "variables": [
        {
            "annotations": [],
            "location": {
                "column": 16,
                "line": 47
            },
            "modifiers": [],
            "name": "str",
            "references": [],
            "type": "String"
        },
        {
            "annotations": [],
            "location": {
                "column": 36,
                "line": 83
            },
            "modifiers": [],
            "name": "hhId",
            "references": [],
            "type": "Id"
        },
        {
            "annotations": [],
            "location": {
                "column": 20,
                "line": 88
            },
            "modifiers": [],
            "name": "strSoql",
            "references": [],
            "type": "String"
        },
        {
            "annotations": [],
            "location": {
                "column": 20,
                "line": 89
            },
            "modifiers": [],
            "name": "strComma",
            "references": [],
            "type": "String"
        },
        {
            "annotations": [],
            "location": {
                "column": 21,
                "line": 90
            },
            "modifiers": [],
            "name": "isHHAccount",
            "references": [],
            "type": "Boolean"
        },
        {
            "annotations": [],
            "location": {
                "column": 26,
                "line": 91
            },
            "modifiers": [],
            "name": "listStrFld",
            "references": [],
            "type": "LIST"
        },
        {
            "annotations": [],
            "location": {
                "column": 20,
                "line": 92
            },
            "modifiers": [],
            "name": "strObject",
            "references": [],
            "type": "String"
        },
        {
            "annotations": [],
            "location": {
                "column": 25,
                "line": 95
            },
            "modifiers": [],
            "name": "strF",
            "references": [],
            "type": "String"
        },
        {
            "annotations": [],
            "location": {
                "column": 37,
                "line": 96
            },
            "modifiers": [],
            "name": "dfr",
            "references": [],
            "type": "DescribeFieldResult"
        },
        {
            "annotations": [],
            "location": {
                "column": 70,
                "line": 115
            },
            "modifiers": [],
            "name": "isHHAccount",
            "references": [],
            "type": "Boolean"
        },
        {
            "annotations": [],
            "location": {
                "column": 22,
                "line": 116
            },
            "modifiers": [],
            "name": "listFields",
            "references": [],
            "type": "LIST"
        },
        {
            "annotations": [],
            "location": {
                "column": 48,
                "line": 141
            },
            "modifiers": [],
            "name": "hhId",
            "references": [],
            "type": "Id"
        },
        {
            "annotations": [],
            "location": {
                "column": 20,
                "line": 147
            },
            "modifiers": [],
            "name": "strSoql",
            "references": [],
            "type": "String"
        },
        {
            "annotations": [],
            "location": {
                "column": 27,
                "line": 158
            },
            "modifiers": [],
            "name": "listCon",
            "references": [],
            "type": "LIST"
        },
        {
            "annotations": [],
            "location": {
                "column": 26,
                "line": 160
            },
            "modifiers": [],
            "name": "i",
            "references": [],
            "type": "Integer"
        },
        {
            "annotations": [],
            "location": {
                "column": 22,
                "line": 176
            },
            "modifiers": [],
            "name": "listStrField",
            "references": [],
            "type": "LIST"
        },
        {
            "annotations": [],
            "location": {
                "column": 16,
                "line": 177
            },
            "modifiers": [],
            "name": "strSoql",
            "references": [],
            "type": "String"
        },
        {
            "annotations": [],
            "location": {
                "column": 16,
                "line": 178
            },
            "modifiers": [],
            "name": "strComma",
            "references": [],
            "type": "String"
        },
        {
            "annotations": [],
            "location": {
                "column": 21,
                "line": 179
            },
            "modifiers": [],
            "name": "setCheckUpdate",
            "references": [],
            "type": "Set"
        },
        {
            "annotations": [],
            "location": {
                "column": 21,
                "line": 181
            },
            "modifiers": [],
            "name": "strF",
            "references": [],
            "type": "String"
        },
        {
            "annotations": [],
            "location": {
                "column": 37,
                "line": 185
            },
            "modifiers": [],
            "name": "dfr",
            "references": [],
            "type": "DescribeFieldResult"
        },
        {
            "annotations": [],
            "location": {
                "column": 25,
                "line": 211
            },
            "modifiers": [],
            "name": "setContactFields",
            "references": [],
            "type": "Set"
        },
        {
            "annotations": [],
            "location": {
                "column": 21,
                "line": 254
            },
            "modifiers": [],
            "name": "setContactFields",
            "references": [],
            "type": "Set"
        },
        {
            "annotations": [],
            "location": {
                "column": 46,
                "line": 280
            },
            "modifiers": [],
            "name": "strSObject",
            "references": [],
            "type": "String"
        },
        {
            "annotations": [],
            "location": {
                "column": 42,
                "line": 283
            },
            "modifiers": [],
            "name": "dresult",
            "references": [],
            "type": "DescribeSObjectResult"
        },
        {
            "annotations": [],
            "location": {
                "column": 53,
                "line": 296
            },
            "modifiers": [],
            "name": "listCon",
            "references": [],
            "type": "LIST"
        },
        {
            "annotations": [],
            "location": {
                "column": 27,
                "line": 306
            },
            "modifiers": [],
            "name": "listInsert",
            "references": [],
            "type": "LIST"
        },
        {
            "annotations": [],
            "location": {
                "column": 27,
                "line": 307
            },
            "modifiers": [],
            "name": "listUpdate",
            "references": [],
            "type": "LIST"
        },
        {
            "annotations": [],
            "location": {
                "column": 26,
                "line": 308
            },
            "modifiers": [],
            "name": "listStrFld",
            "references": [],
            "type": "LIST"
        },
        {
            "annotations": [],
            "location": {
                "column": 26,
                "line": 310
            },
            "modifiers": [],
            "name": "con",
            "references": [],
            "type": "Contact"
        },
        {
            "annotations": [],
            "location": {
                "column": 25,
                "line": 311
            },
            "modifiers": [],
            "name": "con2",
            "references": [],
            "type": "Contact"
        },
        {
            "annotations": [],
            "location": {
                "column": 33,
                "line": 331
            },
            "modifiers": [],
            "name": "dml",
            "references": [],
            "type": "DMLOptions"
        },
        {
            "annotations": [],
            "location": {
                "column": 39,
                "line": 333
            },
            "modifiers": [],
            "name": "listSR",
            "references": [],
            "type": "LIST"
        },
        {
            "annotations": [],
            "location": {
                "column": 38,
                "line": 334
            },
            "modifiers": [],
            "name": "sr",
            "references": [],
            "type": "SaveResult"
        },
        {
            "annotations": [],
            "location": {
                "column": 48,
                "line": 371
            },
            "modifiers": [],
            "name": "hh",
            "references": [],
            "type": "SObject"
        },
        {
            "annotations": [],
            "location": {
                "column": 21,
                "line": 374
            },
            "modifiers": [],
            "name": "isHHAccount",
            "references": [],
            "type": "Boolean"
        },
        {
            "annotations": [],
            "location": {
                "column": 20,
                "line": 375
            },
            "modifiers": [],
            "name": "strObject",
            "references": [],
            "type": "String"
        },
        {
            "annotations": [],
            "location": {
                "column": 21,
                "line": 376
            },
            "modifiers": [],
            "name": "hhCopy",
            "references": [],
            "type": "SObject"
        },
        {
            "annotations": [],
            "location": {
                "column": 26,
                "line": 392
            },
            "modifiers": [],
            "name": "listStrFld",
            "references": [],
            "type": "LIST"
        },
        {
            "annotations": [],
            "location": {
                "column": 48,
                "line": 418
            },
            "modifiers": [],
            "name": "hhWinner",
            "references": [],
            "type": "Account"
        },
        {
            "annotations": [],
            "location": {
                "column": 72,
                "line": 418
            },
            "modifiers": [],
            "name": "listHHMerge",
            "references": [],
            "type": "LIST"
        },
        {
            "annotations": [],
            "location": {
                "column": 26,
                "line": 426
            },
            "modifiers": [],
            "name": "loser",
            "references": [],
            "type": "Account"
        },
        {
            "annotations": [],
            "location": {
                "column": 50,
                "line": 442
            },
            "modifiers": [],
            "name": "hh",
            "references": [],
            "type": "SObject"
        },
        {
            "annotations": [],
            "location": {
                "column": 68,
                "line": 442
            },
            "modifiers": [],
            "name": "listCon",
            "references": [],
            "type": "LIST"
        },
        {
            "annotations": [],
            "location": {
                "column": 91,
                "line": 442
            },
            "modifiers": [],
            "name": "listConRemove",
            "references": [],
            "type": "LIST"
        },
        {
            "annotations": [],
            "location": {
                "column": 119,
                "line": 442
            },
            "modifiers": [],
            "name": "listHHMerge",
            "references": [],
            "type": "LIST"
        },
        {
            "annotations": [],
            "location": {
                "column": 55,
                "line": 468
            },
            "modifiers": [],
            "name": "hh",
            "references": [],
            "type": "SObject"
        },
        {
            "annotations": [],
            "location": {
                "column": 73,
                "line": 468
            },
            "modifiers": [],
            "name": "listCon",
            "references": [],
            "type": "LIST"
        },
        {
            "annotations": [],
            "location": {
                "column": 26,
                "line": 471
            },
            "modifiers": [],
            "name": "con",
            "references": [],
            "type": "Contact"
        },
        {
            "annotations": [],
            "location": {
                "column": 32,
                "line": 474
            },
            "modifiers": [],
            "name": "hn",
            "references": [],
            "type": "HH_HouseholdNaming"
        },
        {
            "annotations": [],
            "location": {
                "column": 20,
                "line": 475
            },
            "modifiers": [],
            "name": "strExclusions",
            "references": [],
            "type": "String"
        },
        {
            "annotations": [],
            "location": {
                "column": 52,
                "line": 499
            },
            "modifiers": [],
            "name": "hhId",
            "references": [],
            "type": "Id"
        },
        {
            "annotations": [],
            "location": {
                "column": 75,
                "line": 499
            },
            "modifiers": [],
            "name": "listAddrExisting",
            "references": [],
            "type": "LIST"
        },
        {
            "annotations": [],
            "location": {
                "column": 30,
                "line": 505
            },
            "modifiers": [],
            "name": "listAddr",
            "references": [],
            "type": "LIST"
        },
        {
            "annotations": [],
            "location": {
                "column": 25,
                "line": 506
            },
            "modifiers": [],
            "name": "setAddrKey",
            "references": [],
            "type": "Set"
        },
        {
            "annotations": [],
            "location": {
                "column": 33,
                "line": 510
            },
            "modifiers": [],
            "name": "addr",
            "references": [],
            "type": "Address__c"
        },
        {
            "annotations": [],
            "location": {
                "column": 21,
                "line": 521
            },
            "modifiers": [],
            "name": "hh",
            "references": [],
            "type": "SObject"
        },
        {
            "annotations": [],
            "location": {
                "column": 27,
                "line": 522
            },
            "modifiers": [],
            "name": "listCon",
            "references": [],
            "type": "LIST"
        },
        {
            "annotations": [],
            "location": {
                "column": 24,
                "line": 525
            },
            "modifiers": [],
            "name": "addr",
            "references": [],
            "type": "Address__c"
        },
        {
            "annotations": [],
            "location": {
                "column": 20,
                "line": 546
            },
            "modifiers": [],
            "name": "strKey",
            "references": [],
            "type": "String"
        },
        {
            "annotations": [],
            "location": {
                "column": 26,
                "line": 551
            },
            "modifiers": [],
            "name": "con",
            "references": [],
            "type": "Contact"
        },
        {
            "annotations": [],
            "location": {
                "column": 29,
                "line": 570
            },
            "modifiers": [],
            "name": "setFields",
            "references": [],
            "type": "Set"
        },
        {
            "annotations": [],
            "location": {
                "column": 24,
                "line": 572
            },
            "modifiers": [],
            "name": "strSoql",
            "references": [],
            "type": "String"
        },
        {
            "annotations": [],
            "location": {
                "column": 24,
                "line": 573
            },
            "modifiers": [],
            "name": "strComma",
            "references": [],
            "type": "String"
        },
        {
            "annotations": [],
            "location": {
                "column": 29,
                "line": 575
            },
            "modifiers": [],
            "name": "strF",
            "references": [],
            "type": "String"
        },
        {
            "annotations": [],
            "location": {
                "column": 41,
                "line": 577
            },
            "modifiers": [],
            "name": "dfr",
            "references": [],
            "type": "DescribeFieldResult"
        },
        {
            "annotations": [],
            "location": {
                "column": 34,
                "line": 585
            },
            "modifiers": [],
            "name": "listAddrHH",
            "references": [],
            "type": "LIST"
        },
        {
            "annotations": [],
            "location": {
                "column": 33,
                "line": 586
            },
            "modifiers": [],
            "name": "addrT",
            "references": [],
            "type": "Address__c"
        },
        {
            "annotations": [],
            "location": {
                "column": 70,
                "line": 616
            },
            "modifiers": [],
            "name": "listCon",
            "references": [],
            "type": "LIST"
        },
        {
            "annotations": [],
            "location": {
                "column": 96,
                "line": 616
            },
            "modifiers": [],
            "name": "listAddrExisting",
            "references": [],
            "type": "LIST"
        },
        {
            "annotations": [],
            "location": {
                "column": 30,
                "line": 622
            },
            "modifiers": [],
            "name": "listAddr",
            "references": [],
            "type": "LIST"
        },
        {
            "annotations": [],
            "location": {
                "column": 25,
                "line": 623
            },
            "modifiers": [],
            "name": "setAddrKey",
            "references": [],
            "type": "Set"
        },
        {
            "annotations": [],
            "location": {
                "column": 33,
                "line": 627
            },
            "modifiers": [],
            "name": "addr",
            "references": [],
            "type": "Address__c"
        },
        {
            "annotations": [],
            "location": {
                "column": 26,
                "line": 634
            },
            "modifiers": [],
            "name": "con",
            "references": [],
            "type": "Contact"
        },
        {
            "annotations": [],
            "location": {
                "column": 28,
                "line": 635
            },
            "modifiers": [],
            "name": "addr",
            "references": [],
            "type": "Address__c"
        },
        {
            "annotations": [],
            "location": {
                "column": 24,
                "line": 645
            },
            "modifiers": [],
            "name": "strKey",
            "references": [],
            "type": "String"
        },
        {
            "annotations": [],
            "location": {
                "column": 40,
                "line": 664
            },
            "modifiers": [],
            "name": "picklistSalutations",
            "references": [],
            "type": "LIST"
        },
        {
            "annotations": [],
            "location": {
                "column": 32,
                "line": 665
            },
            "modifiers": [],
            "name": "listSalutations",
            "references": [],
            "type": "LIST"
        },
        {
            "annotations": [],
            "location": {
                "column": 39,
                "line": 668
            },
            "modifiers": [],
            "name": "entry",
            "references": [],
            "type": "PicklistEntry"
        }
    ]
}